README
flask_evolution.py
setup.py
Flask_Evolution.egg-info/PKG-INFO
Flask_Evolution.egg-info/SOURCES.txt
Flask_Evolution.egg-info/dependency_links.txt
Flask_Evolution.egg-info/not-zip-safe
Flask_Evolution.egg-info/requires.txt
Flask_Evolution.egg-info/top_level.txt