Metadata-Version: 1.0
Name: Flask-Evolution
Version: 0.6
Summary: Simple migrations for Flask/SQLAlchemy projects
Home-page: http://github.com/adamrt/flask-evolution/
Author: Adam Patterson
Author-email: adam@adamrt.com
License: BSD
Platform: any
Classifier: Environment :: Web Environment
Classifier: Intended Audience :: Developers
Classifier: License :: OSI Approved :: BSD License
Classifier: Operating System :: OS Independent
Classifier: Programming Language :: Python
Classifier: Topic :: Internet :: WWW/HTTP :: Dynamic Content
Classifier: Topic :: Software Development :: Libraries :: Python Modules
